setup.py
ethango_probability/Binomialdistribution.py
ethango_probability/Gaussiandistribution.py
ethango_probability/Generaldistribution.py
ethango_probability/__init__.py
ethango_probability.egg-info/PKG-INFO
ethango_probability.egg-info/SOURCES.txt
ethango_probability.egg-info/dependency_links.txt
ethango_probability.egg-info/not-zip-safe
ethango_probability.egg-info/top_level.txt